show_weather/__init__.py
show_weather/show_weather.py
show_weather-0.2.0.dist-info/LICENSE
show_weather-0.2.0.dist-info/METADATA
show_weather-0.2.0.dist-info/WHEEL
show_weather-0.2.0.dist-info/entry_points.txt
show_weather-0.2.0.dist-info/top_level.txt
show_weather-0.2.0.dist-info/RECORD
