Metadata-Version: 2.1
Name: show-weather
Version: 0.2.0
Summary: Tells you the weather of any city/town anywhere in the world over the command line
Author: Max Besley
Author-email: <besleymax@gmail.com>
Project-URL: Repository, https://github.com/MaxBesley/show-weather-command
Project-URL: Bug Tracker, https://github.com/MaxBesley/show-weather-command/issues
Classifier: Programming Language :: Python :: 3
Classifier: Operating System :: OS Independent
Classifier: License :: OSI Approved :: MIT License
Classifier: Environment :: Console
Requires-Python: >=3.8
License-File: LICENSE
Requires-Dist: requests >=2.31.0
